FODGE/__init__.py
FODGE/main.py
FODGE/main_functions.py
FODGE/GEA/__init__.py
FODGE/GEA/all_gea.py
FODGE/GEA/gae_pytorch/__init__.py
FODGE/GEA/gae_pytorch/gae/__init__.py
FODGE/GEA/gae_pytorch/gae/layers.py
FODGE/GEA/gae_pytorch/gae/model.py
FODGE/GEA/gae_pytorch/gae/my_init.py
FODGE/GEA/gae_pytorch/gae/optimizer.py
FODGE/GEA/gae_pytorch/gae/train.py
FODGE/GEA/gae_pytorch/gae/utils.py
FODGE/GEA/gcn/__init__.py
FODGE/GEA/gcn/layers.py
FODGE/GEA/gcn/models.py
FODGE/GEA/gcn/utils.py
FODGE/datasets/facebook-wosn-wall.txt
FODGE/datasets/facebook_friendships.txt
FODGE/datasets/fb-wosn-friends.txt
FODGE/embeddings/empty_embedding.npy
FODGE/evaluation_tasks/__init__.py
FODGE/evaluation_tasks/calculate_non_edges.py
FODGE/evaluation_tasks/example_non_edges.csv
FODGE/evaluation_tasks/linear_regression_link_prediction.py
FODGE/evaluation_tasks/scores_utils.py
FODGE/evaluation_tasks/temporal_link_prediction.py
FODGE/evaluation_tasks/tlp_utils.py
FODGE/fodge/LUR.py
FODGE/fodge/__init__.py
FODGE/fodge/fodge_utils.py
FODGE/fodge/load_data.py
FODGE/fodge/run_fodge.py
FODGE-0.0.11.dist-info/METADATA
FODGE-0.0.11.dist-info/WHEEL
FODGE-0.0.11.dist-info/top_level.txt
FODGE-0.0.11.dist-info/RECORD
