Metadata-Version: 2.1
Name: FODGE
Version: 0.0.11
Summary: Dynamic graph embedding algorithm (DGEA) to gradually shift the projection of modified vertices
Home-page: https://github.com/AmitKabya/FODGE
Author: Shoval Fridman
Maintainer: Amit Kabya
Maintainer-email: kabya.amit@gmail.com
License: MIT
Keywords: graphs networks graph-embeddings
Requires-Python: >=3.6.8
Requires-Dist: setuptools (>=61.3.1)
